Metadata-Version: 2.1
Name: vjscraper-tk
Version: 0.0.2
Summary: Scraper de views do TikTok
Author: Renan de Souza Rodrigues
Author-email: renanrodrigues7110@gmail.com
License: MIT License
Keywords: vjscraper,tiktok,tiktok-scraper,vjscraper-tk
License-File: LICENCE
Requires-Dist: playwright
